{
    "properties": {
        "displayName": "Ensure that 'Java version' is the latest, if used to run the web app CIS Control 9.9.",
        "description": "Periodically, newer versions are released for Java software either due to security flaws or to include additional functionality. Using the latest Java version for web apps is recommended in order to take advantage of security fixes, if any, and/or new functionalities of the newer version.",
        "mode": "All",
        "metadata": {
            "category": "CIS"
        }
    }
}